{
  "$schema": "https://schema.management.azure.com/schemas/2019-04-01/deploymentTemplate.json#",
  "contentVersion": "1.0.0.0",
  "resources": [
    {
      "type": "Microsoft.Compute/virtualMachines",
      "apiVersion": "2021-03-01",
      "name": "[parameters('vmName')]",
      "location": "[parameters('location')]",
      "properties": {
        "hardwareProfile": {
          "vmSize": "[parameters('vmSize')]"
        },
        "storageProfile": {
          "imageReference": {
            "publisher": "[parameters('imagePublisher')]",
            "offer": "[parameters('imageOffer')]",
            "sku": "[parameters('imageSku')]",
            "version": "latest"
          },
          "osDisk": {
            "createOption": "FromImage",
            "managedDisk": {
              "storageAccountType": "[parameters('osDiskType')]"
            }
          }
        },
        "osProfile": {
          "computerName": "[parameters('vmName')]",
          "adminUsername": "[parameters('adminUsername')]",
          "adminPassword": "[parameters('adminPassword')]",
          "customData": "[parameters('customData')]"
        },
        "networkProfile": {
          "networkInterfaces": [
            {
              "id": "[resourceId('Microsoft.Network/networkInterfaces', parameters('nicName'))]"
            }
          ]
        }
      },
      "dependsOn": [
        "[resourceId('Microsoft.Network/networkInterfaces', parameters('nicName'))]"
      ]
    },
    {
      "type": "Microsoft.Network/networkInterfaces",
      "apiVersion": "2021-02-01",
      "name": "[parameters('nicName')]",
      "location": "[parameters('location')]",
      "properties": {
        "ipConfigurations": [
          {
            "name": "ipconfig1",
            "properties": {
              "subnet": {
                "id": "[resourceId('Microsoft.Network/virtualNetworks/subnets', parameters('vnetName'), parameters('subnetName'))]"
              },
              "publicIpAddress": {
                "id": "[resourceId('Microsoft.Network/publicIPAddresses', parameters('publicIpName'))]"
              }
            }
          }
        ]
      }
    },
    {
      "type": "Microsoft.Network/publicIPAddresses",
      "apiVersion": "2021-02-01",
      "name": "[parameters('publicIpName')]",
      "location": "[parameters('location')]",
      "properties": {
        "publicIPAllocationMethod": "Dynamic"
      }
    }
  ],
  "parameters": {
    "vmName": {
      "type": "string",
      "metadata": {
        "description": "Name of the virtual machine."
      }
    },
    "location": {
      "type": "string",
      "metadata": {
        "description": "Location for all resources."
      }
    },
    "vmSize": {
      "type": "string",
      "metadata": {
        "description": "Size of the virtual machine."
      }
    },
    "imagePublisher": {
      "type": "string",
      "metadata": {
        "description": "Publisher of the image."
      }
    },
    "imageOffer": {
      "type": "string",
      "metadata": {
        "description": "Offer of the image."
      }
    },
    "imageSku": {
      "type": "string",
      "metadata": {
        "description": "SKU of the image."
      }
    },
    "osDiskType": {
      "type": "string",
      "metadata": {
        "description": "Type of the OS disk."
      }
    },
    "adminUsername": {
      "type": "string",
      "metadata": {
        "description": "Admin username for the VM."
      }
    },
    "adminPassword": {
      "type": "securestring",
      "metadata": {
        "description": "Admin password for the VM."
      }
    },
    "customData": {
      "type": "string",
      "metadata": {
        "description": "Custom data for the VM."
      }
    },
    "nicName": {
      "type": "string",
      "metadata": {
        "description": "Name of the network interface."
      }
    },
    "vnetName": {
      "type": "string",
      "metadata": {
        "description": "Name of the virtual network."
      }
    },
    "subnetName": {
      "type": "string",
      "metadata": {
        "description": "Name of the subnet."
      }
    },
    "publicIpName": {
      "type": "string",
      "metadata": {
        "description": "Name of the public IP address."
      }
    }
  }
}